ussy/__init__.py
ussy/ussify.py
ussy-1.0.4.dist-info/LICENSE
ussy-1.0.4.dist-info/METADATA
ussy-1.0.4.dist-info/WHEEL
ussy-1.0.4.dist-info/top_level.txt
ussy-1.0.4.dist-info/RECORD
